gmaillite/__init__.py
gmaillite/gmail_auto.py
gmaillite-0.2.12.dist-info/LICENSE
gmaillite-0.2.12.dist-info/METADATA
gmaillite-0.2.12.dist-info/WHEEL
gmaillite-0.2.12.dist-info/RECORD
